onshape_variables/__init__.py
onshape_variables/variables.py
onshape_variables-0.1.0.dist-info/METADATA
onshape_variables-0.1.0.dist-info/WHEEL
onshape_variables-0.1.0.dist-info/RECORD
