Metadata-Version: 2.1
Name: onshape-variables
Version: 0.1.0
Summary: A python class to easily interact with Onshape's Variables API
Home-page: https://github.com/csamid/onshape-variables
License: MIT
Author: seasam
Author-email: samidceb@gmail.com
Requires-Python: >=3.9,<4.0
Classifier: License :: OSI Approved :: MIT License
Classifier: Programming Language :: Python :: 3
Classifier: Programming Language :: Python :: 3.9
Classifier: Programming Language :: Python :: 3.10
Classifier: Programming Language :: Python :: 3.11
Requires-Dist: requests (>=2.31.0,<3.0.0)
Project-URL: Repository, https://github.com/csamid/onshape-variables
